[1,0,0,[["cc.JsonAsset",["_name","json"],1]],[[0,0,1,3]],[[0,"round",{"round":{"title1":"高级召唤返利","title2":"先知圣堂返利","title3":"神器宝库返利","title4":"羁绊召唤返利","title5":"神器锻造返利","title6":"超凡召唤返利","unlock_tips1":"活动未开启","unlock_tips2":"请先完成上一轮任务！","unlock":"上一轮任务还未完成，暂时无法解锁","lock_desc":"每完成一轮任务后会进入下一轮任务","no_open":"活动暂未开启！","help1":"1.活动期间内，在英雄神殿中进行高级召唤达到指定次数就可以领取对应奖励。\n\n2.活动期间内会有多轮任务，完成上一轮才可以解锁下一轮任务。\n\n3.活动每期重置。","help2":"1.活动期间内，在先知圣堂中招募达到指定次数就可以领取对应奖励。\n\n2.活动期间内会有多轮任务，完成上一轮才可以解锁下一轮任务。\n\n3.活动每期重置。","help3":"1.活动期间内，在神器宝库中祈祷达到指定次数就可以领取对应奖励。\n\n2.活动期间内会有多轮任务，完成上一轮才可以解锁下一轮任务。\n\n3.活动每期重置。","help4":"1.活动期间内，在英雄神殿中进行羁绊召唤达到指定次数就可以领取对应奖励。\n\n2.活动期间内会有多轮任务，完成上一轮才可以解锁下一轮任务。\n\n3.活动每期重置。","help5":"1.活动期间内，在天赐神兵中神器锻造达到指定次数就可以领取对应奖励。\n\n2.活动期间内会有多轮任务，完成上一轮才可以解锁下一轮任务。\n\n3.活动每期重置。","help6":"1.活动期间内，在深渊魔影和天境神恩中进行超凡召唤达到指定次数就可以领取对应奖励。\n\n2.活动每期重置。","unlock_btn":"未解锁","button":"第{0}轮","sub_title1":"限时返利","sub_title2":"限时返利","sub_title3":"限时返利","sub_title4":"限时返利","sub_title5":"限时返利","sub_title6":"限时返利","complete":"已完成","btn1":"高级召唤","btn2":"先知圣堂","btn3":"神器宝库","btn4":"羁绊召唤","btn5":"神器锻造","btn6":"超凡召唤","lock_desc1":"达到累积召唤次数，即可获得奖励","note_round_task_complete":"{0}完成","btn8":"普通召唤","title8":"普通召唤返利","sub_title8":"普通召唤返利","jumptarget1_300400":"战役基金","jumptarget1_300401":"地宫基金","jumptarget1_300402":"高级召唤战令","jumptarget1_300403":"神器召唤战令","jumptarget1_300404":"先知召唤战令","title1_1":"高级召唤返利","title2_1":"先知圣堂返利","title3_1":"神器宝库返利","title4_1":"羁绊召唤返利","title5_1":"神器锻造返利","title6_1":"超凡召唤返利","title8_1":"普通召唤返利","note_activity_round":"已完成：{0}/{1}","note_activity_end":"{0}即将结束，守护者大人请不要错过获得奖励的机会","title_activity_end":"活动即将结束","title_round_clear":"第{0}轮完成！","title_round_clear_all":"活动完成","btn9":"幻境挑战","title9":"幻境挑战","title9_1":"幻境挑战","title9_2":"幻境挑战","sub_title9":"限时返利","btn10":"深渊讨伐","title10":"深渊讨伐","title10_1":"深渊讨伐","title10_2":"深渊讨伐","sub_title10":"限时返利","btn_total_recharge_daily":"每日奖励","total_recharge_show_ad_1":"限时累充获强力英雄","total_recharge_show_ad_2":"暴击核辅，推图必备","total_recharge_show_ad_3":"限时累充获强力神器","total_recharge_show_ad_4":"不灭圣炎，圣盾免伤","total_recharge_show_ad_5":"限时累充获强力英雄","total_recharge_show_ad_6":"达到指定额度，领额外奖励","note_total_recharge_reward_show":"核心奖励","note_total_recharge_value":"已累充：{0}元","note_total_recharge_des":"充值代金券商店、代金券每日礼包商店、终身限购礼包、代金券限时活动不计入累充，使用代金券时计入","sub_title19":"限时累充","title19_1":"限时累充","title19_2":"限时累充","title19":"限时累充","btn19":"限时累充","tips_daily_reward_tomorrow":"奖励明日刷新"}}]],0,0,[],[],[]]