[1,0,0,[["cc.JsonAsset",["_name","json"],1]],[[0,0,1,3]],[[0,"effect-ui-charistmas-qiandao-qiufudong",{"version":"1.2.33","type":"effect","timelinesData":{"layers":[{"type":"image","path":"../../gui/resources/ui/view/activity_story/christmas/activity_christmas_login_itemdb01","start":0,"playPath":"ui/view/activity_story/christmas/activity_christmas_login_itemdb01","aliasName":"image4","group":"var","id":"xgil66qb","flipDir":"n","centerX":0,"centerY":0,"tweens":{"xy":[{"frame":0,"curveType":0,"x":"0.00","y":"6.00"},{"frame":45,"curveType":0,"x":"0.00","y":"0.00"},{"frame":90,"curveType":0,"x":"0.00","y":"6.00"}]},"initParams":{"frames":1,"premultiply":false}},{"type":"image","path":"../../gui/resources/ui/view/activity_story/christmas/activity_christmas_login_itemdb01","start":0,"playPath":"ui/view/activity_story/christmas/activity_christmas_login_itemdb01","aliasName":"image3","group":"var","id":"jmx0lmyu","flipDir":"n","centerX":0,"centerY":0,"tweens":{"xy":[{"frame":0,"curveType":0,"x":"0.00","y":"3.87"},{"frame":29,"curveType":0,"x":"0.00","y":"0.00"},{"frame":30,"curveType":0,"x":"0.00","y":"0.00"},{"frame":75,"curveType":0,"x":"0.00","y":"6.00"},{"frame":90,"curveType":0,"x":"0.00","y":"4.00"}]},"initParams":{"frames":1,"premultiply":false}},{"type":"image","path":"../../gui/resources/ui/view/activity_story/christmas/activity_christmas_login_itemdb01","start":0,"playPath":"ui/view/activity_story/christmas/activity_christmas_login_itemdb01","aliasName":"image2","group":"var","id":"1ba7emta","flipDir":"n","centerX":0,"centerY":0,"tweens":{"xy":[{"frame":0,"curveType":0,"x":"0.00","y":"1.87"},{"frame":14,"curveType":0,"x":"0.00","y":"0.00"},{"frame":15,"curveType":0,"x":"0.00","y":"0.00"},{"frame":60,"curveType":0,"x":"0.00","y":"6.00"},{"frame":90,"curveType":0,"x":"0.00","y":"2.00"}]},"initParams":{"frames":1,"premultiply":false}},{"type":"image","path":"../../gui/resources/ui/view/activity_story/christmas/activity_christmas_login_itemdb01","start":0,"playPath":"ui/view/activity_story/christmas/activity_christmas_login_itemdb01","aliasName":"image1","group":"var","id":"sf7zhfjg","flipDir":"n","centerX":0,"centerY":0,"tweens":{"xy":[{"frame":0,"curveType":0,"x":"0.00","y":"0.00"},{"frame":45,"curveType":0,"x":"0.00","y":"6.00"},{"frame":90,"curveType":0,"x":"0.00","y":"0.00"}]},"initParams":{"frames":1,"premultiply":false}}]},"libs":{"dict":{}},"materialNames":[]}]],0,0,[],[],[]]