[1,0,0,[["cc.JsonAsset",["_name","json"],1]],[[0,0,1,3]],[[0,"task_template",{"task_template":{"1000000":"Log into game.","1001000":"","1002000":"Buy Gold a total of [0] time(s).","1003000":"","1004000":"Log into the game for a total of [0] day(s).","1005000":"Spend a total of [0] Diamonds.","1006000":"","1007000":"","1008000":"Chat in the World Channel [0] time(s).","1009000":"Perform a total of [0] event summon(s).","1010000":"Recharge a total of [0] time(s).","1011000":"Share event summons [0] time(s).","1012000":"Share the hero [0] one time.","1013000":"Reach [0] points in Unparalleled World.","1100002":"Accumulate [0] Daily Activity.","1101003":"Accumulate [0] Weekly Activity Points.","1102000":"","1103000":"","1200000":"Reach Player Level [0].","1300000":"Have [0] friend(s).","1301000":"Send Friendship Points [0] time(s).","1400000":"Reach [0] Power.","1500000":"Own 1 Hero at Lv.[0].","1501015":"Get [0] Hero(es) to Lv.15.","1501020":"Get [0] Hero(es) to Lv.20.","1501022":"Own [0] Lv.22 hero(es).","1501025":"Get [0] Hero(es) to Lv.25.","1501030":"Get [0] Hero(es) to Lv.30.","1501035":"Get [0] Hero(es) to Lv.35.","1501036":"Get [0] Hero(es) to Lv.36.","1501040":"Get [0] Hero(es) to Lv.40.","1501045":"Get [0] Hero(es) to Lv.45.","1501050":"Get [0] Hero(es) to Lv.50.","1501060":"Get [0] Hero(es) to Lv.60.","1501070":"Get [0] Hero(es) to Lv.70.","1501080":"Get [0] Hero(es) to Lv.80.","1502000":"","1503001":"Get [0] Hero(es) to Ascension Lv.1.","1503002":"Get [0] Hero(es) to Ascension Lv.2.","1503003":"Get [0] Hero(es) to Ascension Lv.3.","1503004":"Get [0] Hero(es) to Ascension Lv.4.","1503005":"Get [0] Hero(es) to Ascension Lv.5.","1503006":"Get [0] Hero(es) to Ascension Lv.6.","1503007":"Get [0] Hero(es) to Ascension Lv.7.","1503008":"Get [0] Hero(es) to Ascension Lv.8.","1504000":"","1505004":"Own [0] 4-Star Hero(es).","1505005":"Own [0] 5-Star Hero(es).","1505006":"Own [0] 6-Star Hero(es).","1505007":"Own [0] 7-Star Hero(es).","1505008":"Own [0] 8-Star Hero(es).","1505009":"Own [0] 9-Star Hero(es).","1505010":"Own [0] 10-Star Hero(es).","1505011":"Own [0] 11-Star Hero(es).","1505012":"Own [0] 12-Star Hero(es).","1505013":"Own [0] 13-Star Hero(es).","1505014":"Own [0] 14-Star Hero(es).","1506006":"","1506007":"","1506008":"","1506009":"","1507006":"","1507007":"","1507008":"","1507009":"","1508006":"","1508007":"","1508008":"","1508009":"","1509006":"","1509007":"","1509008":"","1509009":"","1510006":"","1510007":"","1510008":"","1510009":"","1511010":"","1511011":"","1511012":"","1511013":"","1511014":"","1512000":"","1513000":"","1514000":"","1515000":"","1516000":"Reach a total rating of [0] Hero Archive.","1517001":"Advance any Empire hero to [0] Stars.","1517002":"Advance any Woodland hero to [0] Stars.","1517003":"Advance any Eclipse hero to [0] Stars.","1517004":"Advance any Divine hero to [0] Stars.","1517005":"Advance any Demon hero to [0] Stars.","1518000":"Own [0] non-duplicate hero(es) with the same Valkyrie Synergy.","1518001":"Own [0] non-duplicate Mystifier synergymate(s).","1518002":"Own [0] non-duplicate Valiantor synergymate(s).","1518003":"Own [0] non-duplicate Ethereal synergymate(s).","1518004":"Own [0] non-duplicate Glorian synergymate(s).","1518005":"Own [0] non-duplicate Avenger synergymate(s).","1518006":"Own [0] non-duplicate Doomsdayer synergymate(s).","1519001":"Own [0] non-duplicate hero(es) with the same Faction Synergy activated.","1519002":"Own [0] non-duplicate hero(es) with Dawnbringer synergy activated.","1519003":"Own [0] non-duplicate hero(es) with Verdian synergy activated.","1519004":"Own [0] non-duplicate hero(es) with Shadowarch synergy activated.","1519005":"Own [0] non-duplicate hero(es) with Celestial synergy activated.","1519006":"Own [0] non-duplicate hero(es) with Deviant synergy activated.","1520001":"Own [0] non-duplicate hero(es) with any synergy activated.","1520002":"Own [0] non-duplicate hero(es) with Striker synergy activated.","1520003":"Own [0] non-duplicate hero(es) with Protector synergy activated.","1520004":"Own [0] non-duplicate hero(es) with Phantom synergy activated.","1520005":"Own [0] non-duplicate hero(es) with Enchanter synergy activated.","1520006":"Own [0] non-duplicate hero(es) with Monarch synergy activated.","1521006":"Own [0] 6-Star Legendary hero(es) at the same time.","1521007":"Own [0] 7-Star Legendary hero(es) at the same time.","1521008":"Own [0] 8-Star Legendary hero(es) at the same time.","1521009":"Own [0] 9-Star Legendary hero(es) at the same time.","1521010":"Own [0] 10-Star Legendary hero(es) at the same time.","1521011":"Own [0] 11-Star Legendary hero(es) at the same time.","1521012":"Own [0] 12-Star Legendary hero(es) at the same time.","1521013":"Own [0] 13-Star Legendary hero(es) at the same time.","1521014":"Own [0] 14-Star Legendary hero(es) at the same time.","1524101":"","1524102":"","1524103":"","1524104":"","1524105":"","1524106":"","1524201":"","1524202":"","1524203":"","1524204":"","1524205":"","1524206":"","1524301":"","1524302":"","1524303":"","1524304":"","1524305":"","1524306":"","1524401":"","1524402":"","1524403":"","1524404":"","1524405":"","1524406":"","1524501":"","1524502":"","1524503":"","1524504":"","1524505":"","1524506":"","1700000":"Own [0] Relic(s).","1700040":"Own [0] Rare Relic(s).","1700050":"Own [0] Epic Relic(s).","1700060":"Own [0] Legendary Relic(s).","1701002":"Own [0] 2-Star Relic(s).","1701003":"Own [0] 3-Star Relic(s).","1701004":"Own [0] 4-Star Relic(s).","1701005":"Own [0] 5-Star Relic(s).","1702000":"Get the highest-level Relic to Lv.[0].","1702010":"Own [0] Lv.10 Relic(s).","1702015":"Own [0] Lv.15 Relic(s).","1702020":"Own [0] Lv.20 Relic(s).","1702025":"Own [0] Lv.25 Relic(s).","1702030":"Own [0] Lv.30 Relic(s).","1702035":"Own [0] Lv.35 Relic(s).","1702040":"Own [0] Lv.40 Relic(s).","1702045":"Own [0] Lv.45 Relic(s).","1702050":"Own [0] Lv.50 Relic(s).","1702055":"Own [0] Lv.55 Relic(s).","1702060":"Own [0] Lv.60 Relic(s).","1702065":"Own [0] Lv.65 Relic(s).","1702070":"Own [0] Lv.70 Relic(s).","1702075":"Own [0] Lv.75 Relic(s).","1702080":"Own [0] Lv.80 Relic(s).","1702085":"Own [0] Lv.85 Relic(s).","1702090":"Own [0] Lv.90 Relic(s).","1702095":"Own [0] Lv.95 Relic(s).","1702100":"Own [0] Lv.100 Relic(s).","1703000":"","1704007":"Own [0] Ascension Lv.1 Relic(s).","1704014":"Own [0] Ascension Lv.2 Relic(s).","1704021":"Own [0] Ascension Lv.3 Relic(s).","1704028":"Own [0] Ascension Lv.4 Relic(s).","1704035":"Own [0] Ascension Lv.5 Relic(s).","1704056":"Own [0] Ascension Lv.8 Relic(s).","1900020":"Own [0] piece(s) of Common or higher Gear.","1900030":"Own [0] piece(s) of Uncommon or higher Gear.","1900035":"Own [0] piece(s) of Uncommon+ or higher Gear.","1900040":"Own [0] piece(s) of Rare or higher Gear.","1900045":"Own [0] piece(s) of Rare+ or higher Gear.","1900050":"Own [0] piece(s) of Epic or higher Gear.","1900055":"Own [0] piece(s) of Epic+ or higher Gear.","1900060":"Own [0] piece(s) of Legendary or higher Gear.","1901001":"Own [0] piece(s) of Tier 1 Gear.","1901002":"Own [0] piece(s) of Tier 2 Gear.","1901003":"Own [0] piece(s) of Tier 3 Gear.","1902020":"Own [0] Hero(es) equipped with a set of Common or higher Gear.","1902030":"Own [0] Hero(es) equipped with a set of Uncommon or higher Gear.","1902035":"Own [0] Hero(es) equipped with a set of Uncommon+ or higher Gear.","1902040":"Own [0] Hero(es) equipped with a set of Rare or higher Gear.","1902045":"Own [0] Hero(es) equipped with a set of Rare+ or higher Gear.","1902050":"Own [0] Hero(es) equipped with a set of Epic or higher Gear.","1902055":"Own [0] Hero(es) equipped with a set of Epic+ or higher Gear.","1902060":"Own [0] Hero(es) equipped with a set of Legendary or higher Gear.","1903000":"","1904001":"","1905000":"Get highest Enhancement Level Gear to Lv.[0].","1906001":"Own [0] Hero(es) equipped with 4 pieces of Enhancement Lv.10 Gear.","1906003":"Own [0] Hero(es) equipped with 4 pieces of Enhancement Lv.30 Gear.","1906004":"Own [0] Hero(es) equipped with 4 pieces of Enhancement Lv.40 Gear.","1906005":"Own [0] Hero(es) equipped with 4 pieces of Enhancement Lv.50 Gear.","1906006":"Own [0] Hero(es) equipped with 4 pieces of Enhancement Lv.60 Gear.","1906007":"Own [0] Hero(es) equipped with 4 pieces of Enhancement Lv.70 Gear.","1906008":"Own [0] Hero(es) equipped with 4 pieces of Enhancement Lv.80 Gear.","1906009":"Own [0] Hero(es) equipped with 4 pieces of Enhancement Lv.90 Gear.","1907001":"Own [0] piece(s) of Refinement Lv.1 Gear.","1907002":"Own [0] piece(s) of Refinement Lv.2 Gear.","1907003":"Own [0] piece(s) of Refinement Lv.3 Gear.","1907004":"Own [0] piece(s) of Refinement Lv.4 Gear.","1907005":"Own [0] piece(s) of Refinement Lv.5 Gear.","1907006":"Own [0] piece(s) of Refinement Lv.6 Gear.","1907010":"Own [0] piece(s) of Refinement Lv.10 Gear.","1907015":"Own [0] piece(s) of Refinement Lv.15 Gear.","1907020":"Own [0] piece(s) of Refinement Lv.20 Gear.","1908002":"Own [0] Hero(es) equipped with 4 pieces of Refinement Lv.2 Gear.","1908004":"Own [0] Hero(es) equipped with 4 pieces of Refinement Lv.4 Gear.","1908006":"Own [0] hero(es) equipped with 4 pieces of gear at Gear Refinement Lv.6.","1908007":"Own [0] Hero(es) equipped with 4 pieces of Refinement Lv.7 Gear.","1908008":"Own [0] Hero(es) equipped with 4 pieces of Refinement Lv.8 Gear.","1908010":"Own [0] Hero(es) equipped with 4 pieces of Refinement Lv.10 Gear.","1908012":"Own [0] Hero(es) equipped with 4 pieces of Refinement Lv.12 Gear.","1908014":"Own [0] Hero(es) equipped with 4 pieces of Refinement Lv.14 Gear.","1909000":"","1910001":"Own [0] piece(s) of Enchantment Lv.1 Gear.","1910002":"Own [0] piece(s) of Enchantment Lv.2 Gear.","1910003":"Own [0] piece(s) of Enchantment Lv.3 Gear.","1910004":"Own [0] piece(s) of Enchantment Lv.4 Gear.","1910005":"Own [0] piece(s) of Enchantment Lv.5 Gear.","1910006":"Own [0] piece(s) of Enchantment Lv.6 Gear.","1910007":"Own [0] piece(s) of Enchantment Lv.7 Gear.","1910008":"Own [0] piece(s) of Enchantment Lv.8 Gear.","1911000":"","1912001":"Own [0] Hero(es) fully equipped with Enchantment Lv.1 Gear.","1912002":"Own [0] Hero(es) fully equipped with Enchantment Lv.2 Gear.","1912003":"Own [0] hero(es) fully equipped with gear at Gear Enchantment Lv.3.","1913000":"Dismantle [0] Gear of any quality.","1913010":"Dismantle [0] Gear of any quality.","1913030":"Dismantle [0] gear of Uncommon quality.","1914002":"Own [0] Hero(es) equipped with a set of Refinement Lv.2 or higher Gear.","1914004":"Own [0] Hero(es) equipped with a set of Refinement Lv.4 or higher Gear.","1914006":"Own [0] Hero(es) equipped with a set of Refinement Lv.6 or higher Gear.","1914008":"Own [0] Hero(es) equipped with a set of Refinement Lv.8 or higher Gear.","1914010":"Own [0] Hero(es) equipped with a set of Refinement Lv.10 or higher Gear.","1914012":"Own [0] Hero(es) equipped with a set of Refinement Lv.12 or higher Gear.","1914014":"Own [0] Hero(es) equipped with a set of Refinement Lv.14 or higher Gear.","1914016":"Own [0] Hero(es) equipped with a set of Refinement Lv.16 or higher Gear.","1914018":"Own [0] Hero(es) equipped with a set of Refinement Lv.18 or higher Gear.","1914020":"Own [0] Hero(es) equipped with a set of Refinement Lv.20 or higher Gear.","1915000":"Perform any gear upgrade (excluding transfers) [0] time(s).","2100002":"Own [0] Common or higher Rune(s).","2100003":"Own [0] Uncommon or higher Rune(s).","2100004":"Own [0] Rare or higher Rune(s).","2100005":"Own [0] Epic or higher Rune(s).","2100006":"Own [0] Legendary or higher Rune(s).","2101002":"Own [0] Hero(es) equipped with a set of Common Runes.","2101003":"Own [0] Hero(es) equipped with a set of Uncommon Runes.","2101004":"Own [0] Hero(es) equipped with a set of Rare Runes.","2101005":"Own [0] Hero(es) equipped with a set of Epic Runes.","2101006":"Own [0] Hero(es) equipped with a set of Legendary Runes.","2102000":"","2103000":"Get the highest-level Rune to Lv.[0].","2104001":"Own [0] Hero(es) equipped with 2 Lv.10 Runes.","2104002":"Own [0] Hero(es) equipped with 2 Lv.20 Runes.","2104004":"Own [0] Hero(es) equipped with 2 Lv.20 Runes.","2104008":"Own [0] Hero(es) equipped with 2 Lv.80 Runes.","2105001":"Own [0] Blessing Lv.1 Rune(s).","2105002":"Own [0] Blessing Lv.2 Rune(s).","2105003":"Own [0] Blessing Lv.3 Rune(s).","2105005":"Own [0] Rune(s) at Blessing Lv.4.","2105006":"Own [0] Blessing Lv.6 Rune(s).","2105009":"Own [0] Blessing Lv.9 Rune(s).","2105010":"Own [0] Blessing Lv.10 Rune(s).","2105012":"Own [0] Blessing Lv.12 Rune(s).","2105015":"Own [0] Blessing Lv.15 Rune(s).","2106001":"","2107000":"","2108000":"","2109001":"","2110000":"Perform any Rune growth (excluding transfers) [0] time(s).","2300020":"Own [0] Common or higher Hero Talent(s).","2300025":"Own [0] Common+ or higher Hero Talent(s).","2300030":"Own [0] Uncommon or higher Hero Talent(s).","2300035":"Own [0] Uncommon+ or higher Hero Talent(s).","2300040":"Own [0] Rare or higher Hero Talent(s).","2300045":"Own [0] Rare+ or higher Hero Talent(s).","2300050":"Own [0] Epic or higher Hero Talent(s).","2300055":"Own [0] Epic+ or higher Hero Talent(s).","2300060":"Own [0] Legendary or higher Hero Talent(s).","2301000":"Transmute Gems a total of [0] time(s).","2302000":"Craft Gems a total of [0] time(s).","2303020":"Own [0] Hero(es) equipped with a set of Common or higher Gem(s).","2303025":"Own [0] Hero(es) equipped with a set of Common+ or higher Gear.","2303030":"Own [0] Hero(es) equipped with a set of Uncommon or higher Gem(s).","2303035":"Own [0] Hero(es) equipped with a set of Uncommon+ or higher Gem(s).","2303040":"Own [0] Hero(es) equipped with a set of Rare or higher Gem(s).","2303045":"Own [0] Hero(es) equipped with a set of Rare+ or higher Gem(s).","2303050":"Own [0] Hero(es) equipped with a set of Epic or higher Gem(s).","2303055":"Own [0] Hero(es) equipped with a set of Epic+ or higher Gem(s).","2303060":"Own [0] Hero(es) equipped with a set of Legendary or higher Gem(s).","2500000":"Level up Sage's Tome [0] time(s).","2501000":"","2502000":"","2503000":"In Sage's Tome, level up the x Skill to Lv.[0].","2504000":"In Sage's Tome, level up any Skill [0] time(s).","2700000":"Fully activate [0] story chapter(s) in the Realm.","2800000":"Use Idle Speed-up [0] times.","2801000":"Clear Mission [0].","2802000":"Spent Diamonds for Idle Speed-ups [0] time(s).","3800000":"Accept [0] Bounty Quest(s).","3800004":"Accept [0] Rare Bounty Quest(s).","3800005":"Accept [0] Legendary Bounty Quest(s).","3800006":"Accept [0] Mythic Bounty Quest(s).","3801000":"Accept [0] Rare or higher Bounty Quest(s).","3802000":"","3803000":"Complete [0] Bounty Quest(s).","3804000":"Complete [0] Common or higher Bounty Quest(s).","3805000":"Complete [0] Uncommon or higher Bounty Quest(s).","3806000":"Complete [0] Rare or higher Bounty Quest(s).","3807000":"Complete [0] Epic or higher Bounty Quest(s).","3808000":"Complete [0] Legendary or higher Bounty Quest(s).","3900000":"Perform [0] Summons at the Hall of Heroes.","3900003":"Perform [0] Advanced Summon(s).","3901000":"Perform [0] Oracle Summon(s).","3902000":"Perform [0] Relic Summon(s).","3903000":"Pray at the Relic Vault and obtain [0] Relic(s) of Rare quality or higher.","3904000":"At the Relic Vault, obtain [0] Relic(s) of Rare quality or higher.","4100000":"Refresh items [0] time(s) at the Mystery Shop.","4101000":"Buy items [0] time(s) at the Mystery Shop.","4102000":"","4103000":"","4104000":"Buy any item from the Merchant Guild [0] time(s).","4105000":"Buy Ascension Ores in Limited Deals [0] time(s).","4106000":"Buy Refinement Ores in the Arena Shop [0] time(s).","4107000":"Buy any item from the Guild Shop [0] time(s).","4108000":"Buy any item from the Celestial Shop [0] time(s).","4109000":"Buy any item from the Gloom Shop [0] time(s).","4110000":"Buy any item from the Oracle Shop [0] time(s).","4111000":"Buy any item from the Relic Shop [0] time(s).","4112010":"Buy Gear of any quality in the Arena Shop [0] time(s).","4112040":"Buy Rare Gear in the Arena Shop [0] time(s).","4113000":"Buy any item from Limited Deals [0] time(s).","4200000":"Participate in the Arena [0] time(s).","4201000":"Win in the Arena [0] time(s).","4202000":"Reach Arena Rank [0].","4203000":"Participate in the Arena [0] time(s).","4204000":"","4205000":"","4206000":"In the Arena, reach tier","4207000":"Buy challenge attempts in the Arena [0] time(s).","4300000":"Clear or sweep the Forgotten Land [0] time(s).","4301000":"Achieve [0] stars in the Forgotten Land.","4302045":"Clear Floor [0] in Corrupt Spring.","4302046":"Clear Floor [0] in Wailing Mines.","4302047":"Clear Floor [0] in Crystal Woods.","4302048":"Clear Floor [0] in Crimson Town.","4303000":"","4304045":"Challenge [0] time(s) in FL—Corrupt Spring.","4304046":"Challenge [0] time(s) in FL—Wailing Mines.","4304047":"Challenge [0] time(s) in FL—Crystal Woods.","4304048":"Challenge [0] time(s) in FL—Crimson Town.","4305000":"Buy a challenge attempt for any Forgotten Land instance [0] time(s).","4305047":"Buy challenge attempts in Crystal Woods [0] time(s).","4400000":"Clear [0] floor(s) in Palace of Penrose.","4401000":"Clear Palace of Penrose or claim daily rewards [0] time(s).","4402000":"Clear Palace of Penrose or claim daily rewards [0] time(s).","4403000":"","4500000":"Challenge [0] time(s) in the Grayshroom Realm","4501000":"Clear Grayshroom Realm Chapter [0].","4502000":"","4503000":"","4504000":"Buy challenge attempts in Grayshroom Realm [0] time(s).","4505000":"In Grayshroom Realm, open Chests [0] time(s).","4506000":"In Grayshroom Realm, reach [0] damage in single instance of damage.","4507000":"In Grayshroom Realm, clear all chapters up to Chapter [0].","4600000":"Defeat the final boss in the Labyrinth [0] time(s).","4601000":"Defeat a total of [0] enemies in the Labyrinth.","4602000":"","4603000":"","4604000":"","4605000":"","4606000":"","4607000":"","4608000":"","4609000":"","4610000":"","4611000":"Defeat a total of [0] enemies in the Labyrinth's Nightmare mode.","4700000":"Defeat or sweep Elite Enemies in Legend Archive [0] time(s).","4701000":"Clear Legend Archive—Elite Enemy Stage [0].","4702000":"Complete [0] Hero Lore(s).","4800000":"Clear or sweep the Celestial Trials [0] time(s).","4801000":"Clear [0] floor(s) in any Celestial Trial.","4801001":"Clear [0] floor(s) in Celestial Trials—Imperial Glory.","4801002":"Clear [0] floor(s) in Celestial Trials—Woodland's Breath.","4801003":"Clear [0] floor(s) in Celestial Trials—Tide of Eclipse.","4801004":"Clear [0] floor(s) in Celestial Trials—Divine Legend.","4801005":"Clear [0] floor(s) in Celestial Trials—Demon Tide.","4801006":"","4802000":"Attempt any Celestial Trial [0] time(s).","4900000":"Grow [0] Vileflower(s) in the Gloomwoods.","4901006":"Grow [0] Legendary Vileflower(s) in the Gloomwoods.","4902000":"","4903000":"Pillage [0] times in the Gloomwoods.","4904000":"","4905001":"Grow [0] Vileflower(s) in the Gloomwoods' Peace mode.","4905002":"Grow [0] Vileflower(s) in the Gloomwoods' Pillage mode.","5000000":"Clear Lost City (Ch.[0]).","5001000":"Achieve [0] stars in Lost City.","5002000":"Clear Lost City [0] time(s).","5003000":"","5100000":"","5100001":"","5100002":"","5110001":"Activate [0] Talent(s).","5111001":"Perform Talent upgrading [0] time(s).","5112001":"Own [0] Uncommon or higher Talent(s).","5113003":"Own [0] Uncommon or higher Hero Talent(s).","5113004":"Own [0] Rare or higher Hero Talent(s).","5113005":"Own [0] Epic or higher Hero Talent(s).","5113006":"Own [0] Legendary or higher Hero Talent(s).","5200000":"Benedicted Heroes' level reaches [0].","5201000":"Unlock [0] hero slot(s) at Sanctuary of Eve.","5202000":"Reach Revelation Lv.[0] at Sanctuary of Eve.","5300000":"","5301000":"","5400000":"","5401000":"","5500000":"Use Stannard's [Battlewill Apostles] synergy to clear Missions [0] time(s).","5501000":"Use Dorabella's [Vitality Healers] synergy to clear Palace of Penrose [0] time(s).","5502000":"Use any team with 3 or more synergymates to clear Missions or Palace of Penrose [0] time(s).","5502002":"Use any team with 2 or more synergymates to clear Missions or Palace of Penrose [0] time(s).","5503000":"Activate a total of [0] Synergy(ies).","5504000":"Activate a total of [0] Synergy(ies) of 3 or more members.","5505000":"Activate Dorabella's [Vitality Healers] synergy.","5600000":"Participate in Yggdrasil Supremacy [0] time(s).","5600001":"Own [0] Insignias in Helheim","5600002":"Own [0] Insignias in Svartalfheim","5600003":"Own [0] Insignias in Midgard","5600004":"Own [0] Insignias in Alfheim","5700000":"Reach Valkyrie Manor Lv.[0].","5701000":"Touch a Valkyrie [0] time(s).","5702000":"Gift a total of [0] Favor item(s).","5703000":"Unlock [0] Valkyrie(s).","5704000":"Reach Favor Lv.[0] for any Valkyrie.","5705000":"Clear [0] different Valkyrie Stories."}}]],0,0,[],[],[]]