[1,0,0,[["cc.JsonAsset",["_name","json"],1]],[[0,0,1,3]],[[0,"effect-ui-shenqijineng6",{"version":"1.2.32","type":"effect","timelinesData":{"layers":[{"type":"image","path":"不导出/sq_image_71401","start":11,"aliasName":"image","group":"var","id":"as36q5kt","flipDir":"n","centerX":0,"centerY":0,"tweens":{"xy":[{"frame":11,"curveType":0,"x":"0.00","y":"-320.00"},{"frame":15,"curveType":0,"x":"0.00","y":"0.00"},{"frame":42,"curveType":0,"x":"0.00","y":"30.00"},{"frame":47,"curveType":0,"x":"0.00","y":"-320.00"}],"color":[{"frame":11,"curveType":0,"a":0,"r":255,"g":255,"b":255},{"frame":15,"curveType":0,"a":255,"r":255,"g":255,"b":255},{"frame":42,"curveType":0,"a":255,"r":255,"g":255,"b":255},{"frame":47,"curveType":0,"a":0,"r":255,"g":255,"b":255}]},"initParams":{"frames":1}},{"type":"spine","path":"sp_djsqrc","start":9,"group":"a1","id":"c5bcab8x","flipDir":"n","centerX":0,"centerY":0,"tweens":{"xy":[{"frame":9,"curveType":0,"x":"0.00","y":"-320.00"},{"frame":14,"curveType":0,"x":"0.00","y":"0.00"},{"frame":44,"curveType":0,"x":"0.00","y":"0.00"},{"frame":49,"curveType":0,"x":"0.00","y":"-320.00"}],"color":[{"frame":9,"curveType":0,"a":0,"r":255,"g":255,"b":255},{"frame":14,"curveType":0,"a":255,"r":255,"g":255,"b":255},{"frame":44,"curveType":0,"a":255,"r":255,"g":255,"b":255},{"frame":49,"curveType":0,"a":0,"r":255,"g":255,"b":255}]},"initParams":{"loop":"true","frames":13},"userSetting":{"content":"1,1,0"},"material":{"fxList":[{"fx":1,"enabled":false,"params":[1,1,1,0.47058823529411764,0.9647058823529412,0.8549019607843137,0,0,0,0]}]}},{"type":"image","path":"txtp/sq_purple_db","start":9,"group":"a1","id":"v90cura5","flipDir":"n","centerX":0,"centerY":0,"tweens":{"xy":[{"frame":9,"curveType":1,"px1":0.2,"px2":0.5,"py1":0.7,"py2":0.8,"x":"0.00","y":"-320.00"},{"frame":14,"curveType":0,"x":"0.00","y":"0.00"},{"frame":44,"curveType":1,"px1":0.2,"px2":0.5,"py1":0.7,"py2":0.8,"x":"0.00","y":"0.00"},{"frame":49,"curveType":0,"x":"0.00","y":"-320.00"}],"color":[{"frame":9,"curveType":0,"a":0,"r":255,"g":255,"b":255},{"frame":14,"curveType":0,"a":255,"r":255,"g":255,"b":255},{"frame":44,"curveType":0,"a":255,"r":255,"g":255,"b":255},{"frame":49,"curveType":0,"a":0,"r":255,"g":255,"b":255}]},"initParams":{"frames":1},"userSetting":{"content":"1,1,0"}}]},"libs":{"dict":{}}}]],0,0,[],[],[]]